{
  "total_jobs": 979,
  "total_companies": 714,
  "top_companies": {
    "Lensa": 23,
    "Shift": 22,
    "DataAnnotation": 20,
    "CVS Health": 20,
    "PwC": 20,
    "Jacobs": 10,
    "Jobot": 10,
    "Deloitte": 9,
    "Canonical": 7,
    "Crowe": 6
  },
  "categories": {
    "Engineering": 123,
    "Healthcare": 208,
    "Sales": 51,
    "Finance": 15,
    "Management": 161,
    "Marketing": 3,
    "HR": 6,
    "Operations": 10,
    "Other": 402
  },
  "top_locations": {
    "Actions, Perspective, Future": 22,
    "Kubernetes at Canonical": 5,
    "USA at FullStack": 2,
    "Senior Associate at PwC": 2,
    "Manager at PwC": 2,
    "(7am - 7:15p) - Full-Time/Part-Time at Calvary Hospital": 1,
    "FT - Day - Remote at UCI Health": 1,
    "Need, Inc. (Win)": 1,
    "HR Generalist/ Coordinator at River Edge Behavioral Health": 1,
    "Straight Nights at Sanford Health": 1
  },
  "updated_at": "2026-01-26T18:23:23.281831+00:00",
  "data_quality": {
    "jobs_with_location": 79,
    "jobs_with_logo": 979,
    "location_coverage": 0.0807,
    "logo_coverage": 1.0,
    "parse_stats": {
      "total_elements": 979,
      "successful": 979,
      "skipped_no_caption": 0,
      "skipped_no_url": 0,
      "parse_failures": 0,
      "with_location": 79,
      "without_location": 900,
      "location_coverage": 0.0807
    },
    "parse_success_rate": 1.0
  }
}